__init__.py
h_message_bus/__init__.py
h_message_bus/adapters/__init__.py
h_message_bus/adapters/nats_message_adapter.py
h_message_bus/adapters/nats_publisher_adapter.py
h_message_bus/adapters/nats_subscriber_adapter.py
h_message_bus/application/__init__.py
h_message_bus/application/message_processor.py
h_message_bus/application/message_publisher.py
h_message_bus/application/message_subcriber.py
h_message_bus/domain/__init__.py
h_message_bus/domain/models/__init__.py
h_message_bus/domain/models/hai_message.py
h_message_bus/infrastructure/__init__.py
h_message_bus/infrastructure/nats_client_repository.py
h_message_bus/infrastructure/nats_config.py
h_message_bus-0.0.41.dist-info/METADATA
h_message_bus-0.0.41.dist-info/WHEEL
h_message_bus-0.0.41.dist-info/top_level.txt
h_message_bus-0.0.41.dist-info/RECORD
