Metadata-Version: 2.4
Name: h_message_bus
Version: 0.0.41
Summary: Message bus integration for HAI
Author-email: shoebill <shoebill.hai@gmail.com>
Classifier: Programming Language :: Python :: 3
Classifier: License :: OSI Approved :: MIT License
Classifier: Operating System :: OS Independent
Requires-Python: >=3.10
Requires-Dist: nats-py~=2.10.0
Provides-Extra: dev
Requires-Dist: pytest; extra == "dev"
